hyperparameters/__init__.py
hyperparameters/hyperparams.py
hyperparameters/ray_tune_hyperparams.py
hyperparameters-0.4.0.dist-info/LICENSE
hyperparameters-0.4.0.dist-info/METADATA
hyperparameters-0.4.0.dist-info/WHEEL
hyperparameters-0.4.0.dist-info/RECORD
