Metadata-Version: 2.1
Name: hyperparameters
Version: 0.4.0
Summary: Define your Hyperparameters once and use in argparse, hypertunning libraries, and as strongly-typed attributes in code!
License: MIT
Author: Oleh Lokshyn
Author-email: olokshyn@gmail.com
Requires-Python: >=3.10,<3.11
Classifier: License :: OSI Approved :: MIT License
Classifier: Programming Language :: Python :: 3
Classifier: Programming Language :: Python :: 3.10
Provides-Extra: ray
Requires-Dist: pydantic (>=1.10.7,<2.0.0)
Requires-Dist: ray[tune] (>=2.4.0,<3.0.0) ; extra == "ray"
Project-URL: Bug Tracker, https://github.com/olokshyn/Hyperparameters/issues
Project-URL: Repository, https://github.com/olokshyn/Hyperparameters
